typtrader.py
api/__init__.py
api/bar_deque.py
api/data_client.py
api/data_proxy.py
api/data_streamer.py
api/docker_handler.py
app/__init__.py
app/asgi.py
app/settings.py
app/urls.py
app/wsgi.py
db/__init__.py
db/admin.py
db/apps.py
db/handler.py
db/models.py
db/paginations.py
db/permissions.py
db/serializers.py
db/stream_urls.py
db/urls.py
db/views.py
db/migrations/0001_initial.py
db/migrations/__init__.py
engine/__init__.py
engine/account.py
engine/bar.py
engine/data.py
engine/execution.py
engine/holdings_tracker.py
engine/portfolio.py
engine/strategy.py
engine/events/__init__.py
engine/events/event.py
engine/events/fill_event.py
engine/events/order_event.py
engine/events/pair_signal_event.py
engine/events/signal_event.py
engine/events/success_events.py
engine/execution_v2/__init__.py
engine/execution_v2/account.py
engine/execution_v2/execution.py
engine/execution_v2/holdings_tracker.py
engine/execution_v2/order.py
engine/execution_v2/portfolio.py
engine/execution_v2/response.py
engine/execution_v2/runner.py
engine/utils/__init__.py
engine/utils/distributed_queue.py
engine/utils/log.py
engine/utils/persist_db.py
operations/__init__.py
operations/db_init_setup.py
operations/strategy_info.py
strategies/__init__.py
strategies/example_strategy.py
tasks/__init__.py
tasks/app.py
tasks/price_tasks.py
ws_utils/__init__.py
typtrader-0.0.1.dist-info/METADATA
typtrader-0.0.1.dist-info/WHEEL
typtrader-0.0.1.dist-info/top_level.txt
typtrader-0.0.1.dist-info/RECORD
